py_ipfs_cid-0.1.0.dist-info/METADATA
py_ipfs_cid-0.1.0.dist-info/WHEEL
py_ipfs_cid/__init__.py
py_ipfs_cid/__init__.pyi
py_ipfs_cid/py.typed
py_ipfs_cid/py_ipfs_cid.cpython-38-x86_64-linux-gnu.so
py_ipfs_cid-0.1.0.dist-info/RECORD
