Metadata-Version: 2.1
Name: py-ipfs-cid
Version: 0.1.0
Classifier: Programming Language :: Rust
Classifier: Programming Language :: Python :: Implementation :: CPython
Classifier: Programming Language :: Python :: Implementation :: PyPy
Requires-Dist: pytest; extra == 'tests'
Provides-Extra: tests
Requires-Python: >=3.7
